CHANGES.txt
README.txt
setup.py
docs/LICENSE.GPL
docs/LICENSE.txt
experimental/__init__.py
experimental.contentcreation.egg-info/PKG-INFO
experimental.contentcreation.egg-info/SOURCES.txt
experimental.contentcreation.egg-info/dependency_links.txt
experimental.contentcreation.egg-info/namespace_packages.txt
experimental.contentcreation.egg-info/not-zip-safe
experimental.contentcreation.egg-info/requires.txt
experimental.contentcreation.egg-info/top_level.txt
experimental/contentcreation/__init__.py
experimental/contentcreation/configure.zcml
experimental/contentcreation/factory.py
experimental/contentcreation/patches.py
experimental/contentcreation/tests.py