Metadata-Version: 1.0
Name: experimental.contentcreation
Version: 1.0rc1
Summary: Experimental performance improvements to content creation
Home-page: http://pypi.python.org/pypi/experimental.contentcreation
Author: Plone Community
Author-email: plone-developers@lists.sourceforge.net
License: GPL
Platform: UNKNOWN
Classifier: Framework :: Plone
Classifier: Programming Language :: Python
